neptune_fetcher/__init__.py
neptune_fetcher/alpha/__init__.py
neptune_fetcher/alpha/_internal.py
neptune_fetcher/alpha/exceptions.py
neptune_fetcher/alpha/filters.py
neptune_fetcher/alpha/runs.py
neptune_fetcher/api/__init__.py
neptune_fetcher/api/api_client.py
neptune_fetcher/cache.py
neptune_fetcher/exceptions.py
neptune_fetcher/fetchable.py
neptune_fetcher/fields.py
neptune_fetcher/internal/__init__.py
neptune_fetcher/internal/api_utils.py
neptune_fetcher/internal/client.py
neptune_fetcher/internal/composition/__init__.py
neptune_fetcher/internal/composition/attribute_components.py
neptune_fetcher/internal/composition/attributes.py
neptune_fetcher/internal/composition/concurrency.py
neptune_fetcher/internal/composition/download_files.py
neptune_fetcher/internal/composition/fetch_metrics.py
neptune_fetcher/internal/composition/fetch_series.py
neptune_fetcher/internal/composition/fetch_table.py
neptune_fetcher/internal/composition/list_attributes.py
neptune_fetcher/internal/composition/list_containers.py
neptune_fetcher/internal/composition/type_inference.py
neptune_fetcher/internal/composition/validation.py
neptune_fetcher/internal/context.py
neptune_fetcher/internal/env.py
neptune_fetcher/internal/filters.py
neptune_fetcher/internal/identifiers.py
neptune_fetcher/internal/output_format.py
neptune_fetcher/internal/pattern.py
neptune_fetcher/internal/retrieval/__init__.py
neptune_fetcher/internal/retrieval/attribute_definitions.py
neptune_fetcher/internal/retrieval/attribute_types.py
neptune_fetcher/internal/retrieval/attribute_values.py
neptune_fetcher/internal/retrieval/files.py
neptune_fetcher/internal/retrieval/metrics.py
neptune_fetcher/internal/retrieval/retry.py
neptune_fetcher/internal/retrieval/search.py
neptune_fetcher/internal/retrieval/series.py
neptune_fetcher/internal/retrieval/split.py
neptune_fetcher/internal/retrieval/util.py
neptune_fetcher/internal/util.py
neptune_fetcher/nql.py
neptune_fetcher/read_only_project.py
neptune_fetcher-0.23.0.dist-info/METADATA
neptune_fetcher-0.23.0.dist-info/WHEEL
neptune_fetcher-0.23.0.dist-info/licenses/LICENSE
neptune_fetcher-0.23.0.dist-info/RECORD
