Metadata-Version: 2.4
Name: neptune-fetcher
Version: 0.23.0
Summary: Neptune Fetcher (DEPRECATED - use neptune-query instead)
License: Apache-2.0
License-File: LICENSE
Keywords: MLOps,ML Experiment Tracking,ML Model Registry,ML Model Store,ML Metadata Store
Author: neptune.ai
Author-email: contact@neptune.ai
Requires-Python: >=3.9,<4.0
Classifier: Development Status :: 7 - Inactive
Classifier: Environment :: Console
Classifier: Intended Audience :: Developers
Classifier: Intended Audience :: Science/Research
Classifier: License :: OSI Approved :: Apache Software License
Classifier: Natural Language :: English
Classifier: Operating System :: MacOS
Classifier: Operating System :: Microsoft :: Windows
Classifier: Operating System :: POSIX
Classifier: Operating System :: Unix
Classifier: Programming Language :: Python :: 3
Classifier: Programming Language :: Python :: 3.9
Classifier: Programming Language :: Python :: 3.10
Classifier: Programming Language :: Python :: 3.11
Classifier: Programming Language :: Python :: 3.12
Classifier: Programming Language :: Python :: 3.13
Classifier: Programming Language :: Python :: 3.14
Classifier: Programming Language :: Python :: Implementation :: CPython
Classifier: Topic :: Scientific/Engineering :: Artificial Intelligence
Classifier: Topic :: Software Development :: Libraries :: Python Modules
Requires-Dist: azure-storage-blob (>=12.7.0,<13.0.0)
Requires-Dist: neptune-api (>=0.17.0,<0.24.0)
Requires-Dist: pandas (>=1.4.0) ; python_version >= "3.10"
Requires-Dist: pandas (>=1.4.0,<2.3.0) ; python_version < "3.10"
Requires-Dist: tqdm (>=4.66.0)
Project-URL: Documentation, https://docs.neptune.ai/fetcher_setup
Project-URL: Homepage, https://neptune.ai/
Project-URL: Repository, https://github.com/neptune-ai/neptune-fetcher
Project-URL: Replacement Package, https://pypi.org/project/neptune-query
Project-URL: Tracker, https://github.com/neptune-ai/neptune-fetcher/issues
